{
  "Time-Slot": [
  {
    "PutRequest": {
      "Item": {
        "ttlp_id": {
          "S": "1151"
        },
        "date": {
          "S": "2022-06-03T22:00"
        },
        "twitter_announcement": {
          "S": "https://twitter.com/Tim_Burgess/status/1526881490021548032"
        },
        "artist": {
          "S": "Def Leppard"
        },
        "artwork_large": {
          "S": "https://i.scdn.co/image/ab67616d0000b273af4357e469d6a18ae5bf4c41"
        },
        "replay_feed": {
          "S": "https://timstwitterlisteningparty.com/pages/replay/feed_1086.html"
        },
        "artwork_medium": {
          "S": "https://i.scdn.co/image/ab67616d00001e02af4357e469d6a18ae5bf4c41"
        },
        "artwork_small": {
          "S": "https://i.scdn.co/image/ab67616d00004851af4357e469d6a18ae5bf4c41"
        },
        "album": {
          "S": "Diamond Star Halos"
        },
        "twitter_collection": {
          "S": "https://twitter.com/LlSTENlNG_PARTY/timelines/1533725741388554240"
        },
        "release_date": {
          "S": "2022-05-27"
        },
        "album_link": {
          "S": "https://open.spotify.com/album/5arLkguGPIDSGzCT8Cjt6K"
        },
        "twitter_handles": {
          "S": "@DefLeppard:@Tim_Burgess"
        }
      }
    }
  },
  {
    "PutRequest": {
      "Item": {
        "ttlp_id": {
          "S": "1152"
        },
        "date": {
          "S": "2022-06-12T20:00"
        },
        "twitter_announcement": {
          "S": "https://twitter.com/Tim_Burgess/status/1535533290312040453"
        },
        "artist": {
          "S": "Julee Cruise"
        },
        "artwork_large": {
          "S": "https://i.scdn.co/image/ab67616d0000b273e70f4f014070340f0739db30"
        },
        "replay_feed": {
          "S": ""
        },
        "artwork_medium": {
          "S": "https://i.scdn.co/image/ab67616d00001e02e70f4f014070340f0739db30"
        },
        "artwork_small": {
          "S": "https://i.scdn.co/image/ab67616d00004851e70f4f014070340f0739db30"
        },
        "album": {
          "S": "Floating Into The Night"
        },
        "twitter_collection": {
          "S": ""
        },
        "release_date": {
          "S": "1989-09-12"
        },
        "album_link": {
          "S": "https://open.spotify.com/album/3N6VPyK0YsRTccqoRQjkVx"
        },
        "twitter_handles": {
          "S": ""
        }
      }
    }
  },
  {
    "PutRequest": {
      "Item": {
        "ttlp_id": {
          "S": "1153"
        },
        "date": {
          "S": "2022-06-15T21:00"
        },
        "twitter_announcement": {
          "S": "https://twitter.com/LlSTENlNG_PARTY/status/1533729933696049152"
        },
        "artist": {
          "S": "The Dream Machine"
        },
        "artwork_large": {
          "S": "https://pbs.twimg.com/media/FUjnPoYXwAIu4p8?format=jpg&name=large"
        },
        "replay_feed": {
          "S": ""
        },
        "artwork_medium": {
          "S": "https://pbs.twimg.com/media/FUjnPoYXwAIu4p8?format=jpg&name=large"
        },
        "artwork_small": {
          "S": "https://pbs.twimg.com/media/FUjnPoYXwAIu4p8?format=jpg&name=large"
        },
        "album": {
          "S": "Vol: 1 - 3"
        },
        "twitter_collection": {
          "S": ""
        },
        "release_date": {
          "S": "2022"
        },
        "album_link": {
          "S": "https://open.spotify.com/artist/2ngmfPvH3LUeSGOX0kXIgi?si=EEdeMsdlT5yslN2k5ID0Ww"
        },
        "twitter_handles": {
          "S": "@DreamMachineHQ:@Tim_Burgess"
        }
      }
    }
  },
  {
    "PutRequest": {
      "Item": {
        "ttlp_id": {
          "S": "1154"
        },
        "date": {
          "S": "2022-06-16T22:30"
        },
        "twitter_announcement": {
          "S": "https://twitter.com/DavidBowieReal/status/1531965561701380096"
        },
        "artist": {
          "S": "David Bowie"
        },
        "artwork_large": {
          "S": "https://i.scdn.co/image/ab67616d0000b273c41f4e1133b0e6c5fcf58680"
        },
        "replay_feed": {
          "S": ""
        },
        "artwork_medium": {
          "S": "https://i.scdn.co/image/ab67616d00001e02c41f4e1133b0e6c5fcf58680"
        },
        "artwork_small": {
          "S": "https://i.scdn.co/image/ab67616d00004851c41f4e1133b0e6c5fcf58680"
        },
        "album": {
          "S": "The Rise And Fall Of Ziggy Stardust And The Spiders"
        },
        "twitter_collection": {
          "S": ""
        },
        "release_date": {
          "S": "1972-06-06"
        },
        "album_link": {
          "S": "https://open.spotify.com/album/48D1hRORqJq52qsnUYZX56"
        },
        "twitter_handles": {
          "S": "@DavidBowieReal:@Tim_Burgess"
        }
      }
    }
  },
  {
    "PutRequest": {
      "Item": {
        "ttlp_id": {
          "S": "1155"
        },
        "date": {
          "S": "2022-06-18T19:00"
        },
        "twitter_announcement": {
          "S": "https://twitter.com/Tim_Burgess/status/1534481989771862016"
        },
        "artist": {
          "S": "Foals"
        },
        "artwork_large": {
          "S": "https://pbs.twimg.com/media/FUuTPDHWUAAkvnQ?format=jpg&name=small"
        },
        "replay_feed": {
          "S": ""
        },
        "artwork_medium": {
          "S": "https://pbs.twimg.com/media/FUuTPDHWUAAkvnQ?format=jpg&name=small"
        },
        "artwork_small": {
          "S": "https://pbs.twimg.com/media/FUuTPDHWUAAkvnQ?format=jpg&name=small"
        },
        "album": {
          "S": "Life is Yours"
        },
        "twitter_collection": {
          "S": ""
        },
        "release_date": {
          "S": "2022"
        },
        "album_link": {
          "S": "https://open.spotify.com/artist/6FQqZYVfTNQ1pCqfkwVFEa?si=3dubNPZYRjSAX-K0608n-A"
        },
        "twitter_handles": {
          "S": "@foals:@Tim_Burgess"
        }
      }
    }
  },
  {
    "PutRequest": {
      "Item": {
        "ttlp_id": {
          "S": "1156"
        },
        "date": {
          "S": "2022-06-19T21:00"
        },
        "twitter_announcement": {
          "S": "https://twitter.com/LlSTENlNG_PARTY/status/1535888520606363650"
        },
        "artist": {
          "S": "The Feeling"
        },
        "artwork_large": {
          "S": "https://i.scdn.co/image/ab67616d0000b273ae9586dc2e7cd97b76cb1bdf"
        },
        "replay_feed": {
          "S": ""
        },
        "artwork_medium": {
          "S": "https://i.scdn.co/image/ab67616d00001e02ae9586dc2e7cd97b76cb1bdf"
        },
        "artwork_small": {
          "S": "https://i.scdn.co/image/ab67616d00004851ae9586dc2e7cd97b76cb1bdf"
        },
        "album": {
          "S": "Loss. Hope. Love."
        },
        "twitter_collection": {
          "S": ""
        },
        "release_date": {
          "S": "2022-05-06"
        },
        "album_link": {
          "S": "https://open.spotify.com/album/61J7BYB5ewc9Rz7GPFf266"
        },
        "twitter_handles": {
          "S": "@thefeeling:@CptRJones:@DanGSells:@PaulSte87454211:@Tim_Burgess"
        }
      }
    }
  },
  {
    "PutRequest": {
      "Item": {
        "ttlp_id": {
          "S": "1157"
        },
        "date": {
          "S": "2022-06-21T21:00"
        },
        "twitter_announcement": {
          "S": "https://twitter.com/LlSTENlNG_PARTY/status/1533835723010367489"
        },
        "artist": {
          "S": "MELTS"
        },
        "artwork_large": {
          "S": "https://i.scdn.co/image/ab67616d0000b2734f42a4b54d0fe4ebcc6a41b2"
        },
        "replay_feed": {
          "S": ""
        },
        "artwork_medium": {
          "S": "https://i.scdn.co/image/ab67616d00001e024f42a4b54d0fe4ebcc6a41b2"
        },
        "artwork_small": {
          "S": "https://i.scdn.co/image/ab67616d000048514f42a4b54d0fe4ebcc6a41b2"
        },
        "album": {
          "S": "Maelstrom"
        },
        "twitter_collection": {
          "S": ""
        },
        "release_date": {
          "S": "2021-10-19"
        },
        "album_link": {
          "S": "https://open.spotify.com/album/5JvY3v4bGKhJgUJErmhSuc"
        },
        "twitter_handles": {
          "S": "@wearemelts:@Tim_Burgess"
        }
      }
    }
  },
  {
    "PutRequest": {
      "Item": {
        "ttlp_id": {
          "S": "1158"
        },
        "date": {
          "S": "2022-06-22T20:00"
        },
        "twitter_announcement": {
          "S": "https://twitter.com/LlSTENlNG_PARTY/status/1533731524243251206"
        },
        "artist": {
          "S": "Citizens!"
        },
        "artwork_large": {
          "S": "https://i.scdn.co/image/ab67616d0000b273e3186e1c0538ae30233cfe2a"
        },
        "replay_feed": {
          "S": ""
        },
        "artwork_medium": {
          "S": "https://i.scdn.co/image/ab67616d00001e02e3186e1c0538ae30233cfe2a"
        },
        "artwork_small": {
          "S": "https://i.scdn.co/image/ab67616d00004851e3186e1c0538ae30233cfe2a"
        },
        "album": {
          "S": "Here We Are"
        },
        "twitter_collection": {
          "S": ""
        },
        "release_date": {
          "S": "2012-05-28"
        },
        "album_link": {
          "S": "https://open.spotify.com/album/7lkHNu9PjuMg6g6vq55cYW"
        },
        "twitter_handles": {
          "S": "@GoCitizens:@Tim_Burgess"
        }
      }
    }
  },
  {
    "PutRequest": {
      "Item": {
        "ttlp_id": {
          "S": "1159"
        },
        "date": {
          "S": "2022-06-29T21:00"
        },
        "twitter_announcement": {
          "S": "https://twitter.com/LlSTENlNG_PARTY/status/1533459804064256001"
        },
        "artist": {
          "S": "Cud"
        },
        "artwork_large": {
          "S": "https://i.scdn.co/image/ab67616d0000b273624644071e3aa69c2276a782"
        },
        "replay_feed": {
          "S": ""
        },
        "artwork_medium": {
          "S": "https://i.scdn.co/image/ab67616d00001e02624644071e3aa69c2276a782"
        },
        "artwork_small": {
          "S": "https://i.scdn.co/image/ab67616d00004851624644071e3aa69c2276a782"
        },
        "album": {
          "S": "Asquarius"
        },
        "twitter_collection": {
          "S": ""
        },
        "release_date": {
          "S": "2007-01-01"
        },
        "album_link": {
          "S": "https://open.spotify.com/album/4CmyWfydUoXUlfpw0d0vkB"
        },
        "twitter_handles": {
          "S": "@CUDband:@Tim_Burgess"
        }
      }
    }
  }
  ]
}
